structural_lib/__init__.py
structural_lib/__main__.py
structural_lib/adapters.py
structural_lib/api.py
structural_lib/api_results.py
structural_lib/audit.py
structural_lib/bbs.py
structural_lib/beam_pipeline.py
structural_lib/calculation_report.py
structural_lib/compliance.py
structural_lib/constants.py
structural_lib/costing.py
structural_lib/data_types.py
structural_lib/detailing.py
structural_lib/ductile.py
structural_lib/dxf_export.py
structural_lib/error_messages.py
structural_lib/errors.py
structural_lib/etabs_import.py
structural_lib/excel_bridge.py
structural_lib/excel_integration.py
structural_lib/flexure.py
structural_lib/inputs.py
structural_lib/intelligence.py
structural_lib/job_cli.py
structural_lib/job_runner.py
structural_lib/materials.py
structural_lib/models.py
structural_lib/multi_objective_optimizer.py
structural_lib/optimization.py
structural_lib/py.typed
structural_lib/rebar_optimizer.py
structural_lib/report.py
structural_lib/report_svg.py
structural_lib/result_base.py
structural_lib/serialization.py
structural_lib/serviceability.py
structural_lib/shear.py
structural_lib/slenderness.py
structural_lib/tables.py
structural_lib/testing_strategies.py
structural_lib/torsion.py
structural_lib/types.py
structural_lib/utilities.py
structural_lib/validation.py
structural_lib/codes/__init__.py
structural_lib/codes/aci318/__init__.py
structural_lib/codes/ec2/__init__.py
structural_lib/codes/is456/__init__.py
structural_lib/codes/is456/clause_cli.py
structural_lib/codes/is456/compliance.py
structural_lib/codes/is456/detailing.py
structural_lib/codes/is456/ductile.py
structural_lib/codes/is456/flexure.py
structural_lib/codes/is456/load_analysis.py
structural_lib/codes/is456/serviceability.py
structural_lib/codes/is456/shear.py
structural_lib/codes/is456/slenderness.py
structural_lib/codes/is456/tables.py
structural_lib/codes/is456/torsion.py
structural_lib/codes/is456/traceability.py
structural_lib/core/__init__.py
structural_lib/core/base.py
structural_lib_is456-0.19.0.dist-info/licenses/LICENSE
structural_lib_is456-0.19.0.dist-info/METADATA
structural_lib_is456-0.19.0.dist-info/WHEEL
structural_lib_is456-0.19.0.dist-info/top_level.txt
structural_lib_is456-0.19.0.dist-info/RECORD
