Metadata-Version: 2.4
Name: structural-lib-is456
Version: 0.19.0
Summary: IS 456 RC Beam Design Library (flexure, shear, ductile detailing, DXF export for RC beams)
Author: Pravin Surawase
License-Expression: MIT
Project-URL: Homepage, https://github.com/Pravin-surawase/structural_engineering_lib
Project-URL: Repository, https://github.com/Pravin-surawase/structural_engineering_lib
Project-URL: Documentation, https://github.com/Pravin-surawase/structural_engineering_lib/tree/main/docs
Project-URL: Changelog, https://github.com/Pravin-surawase/structural_engineering_lib/blob/main/CHANGELOG.md
Project-URL: Issues, https://github.com/Pravin-surawase/structural_engineering_lib/issues
Classifier: Development Status :: 3 - Alpha
Classifier: Intended Audience :: Developers
Classifier: Topic :: Scientific/Engineering
Classifier: Programming Language :: Python :: 3
Classifier: Programming Language :: Python :: 3.11
Classifier: Programming Language :: Python :: 3.12
Classifier: Programming Language :: Python :: 3.13
Requires-Python: >=3.11
License-File: LICENSE
Requires-Dist: pydantic>=2.0
Provides-Extra: dev
Requires-Dist: pytest; extra == "dev"
Requires-Dist: pytest-cov; extra == "dev"
Requires-Dist: pytest-benchmark; extra == "dev"
Requires-Dist: black; extra == "dev"
Requires-Dist: mypy; extra == "dev"
Requires-Dist: pre-commit; extra == "dev"
Requires-Dist: ruff; extra == "dev"
Requires-Dist: bandit; extra == "dev"
Requires-Dist: isort; extra == "dev"
Requires-Dist: hypothesis>=6.0; extra == "dev"
Provides-Extra: dxf
Requires-Dist: ezdxf>=1.0; extra == "dxf"
Provides-Extra: render
Requires-Dist: ezdxf>=1.0; extra == "render"
Requires-Dist: matplotlib>=3.5; extra == "render"
Provides-Extra: report
Requires-Dist: jinja2>=3.1; extra == "report"
Provides-Extra: pdf
Requires-Dist: reportlab>=4.0; extra == "pdf"
Provides-Extra: validation
Requires-Dist: jsonschema>=4.21; extra == "validation"
Provides-Extra: cad
Requires-Dist: pyvista>=0.43; extra == "cad"
Requires-Dist: stpyvista>=0.1.4; extra == "cad"
Dynamic: license-file
